auditly/__init__.py
auditly/__main__.py
auditly/cli.py
auditly/dep_tree.py
auditly/env_scanner.py
auditly/explain.py
auditly/file_scanner.py
auditly/osv_client.py
auditly/reporter.py
auditly/risk.py
auditly/subdep_scanner.py
auditly/utils.py
auditly-0.1.2.dist-info/licenses/LICENSE
auditly-0.1.2.dist-info/METADATA
auditly-0.1.2.dist-info/WHEEL
auditly-0.1.2.dist-info/entry_points.txt
auditly-0.1.2.dist-info/top_level.txt
auditly-0.1.2.dist-info/RECORD
