Metadata-Version: 2.4
Name: auditly
Version: 0.1.2
Summary: Auditly is a next-generation Python dependency vulnerability scanner that helps developers identify security risks in installed packages and requirements.txt files, providing clear severity levels and fix recommendations.
Home-page: https://github.com/krishnatadi/auditly-pypi
Author: Krishna Tadi
License: MIT
Requires-Python: >=3.7
License-File: LICENSE
Requires-Dist: requests>=2.31.0
Requires-Dist: tqdm>=4.64.0
Dynamic: home-page
Dynamic: license-file
Dynamic: requires-python
